docv/__init__.py
docv/__version__.py
docv/docs.py
docv-1.0.6.dist-info/licenses/LICENSE
docv-1.0.6.dist-info/METADATA
docv-1.0.6.dist-info/WHEEL
docv-1.0.6.dist-info/entry_points.txt
docv-1.0.6.dist-info/top_level.txt
docv-1.0.6.dist-info/RECORD
