Metadata-Version: 2.4
Name: docv
Version: 1.0.6
Summary: A powerful documentation viewer with Vimium-C style keyboard navigation and fully customizable shortcuts.
Home-page: http://github.com/cumulus13/docs
Author: Hadi Cahyadi
Author-email: cumulus13@gmail.com
Maintainer: cumulus13
Maintainer-email: cumulus13@gmail.com
License: MIT
Keywords: documentation viewer vimium-c shortcuts custom
Platform: any
Classifier: Development Status :: 3 - Alpha
Classifier: Intended Audience :: Developers
Classifier: Operating System :: OS Independent
Classifier: Programming Language :: Python
Classifier: Programming Language :: Python :: 3
Classifier: Topic :: Software Development :: Libraries :: Python Modules
Classifier: Topic :: Software Development :: Documentation
License-File: LICENSE
Requires-Dist: pywebview
Requires-Dist: envdot
Provides-Extra: all
Requires-Dist: webview; extra == "all"
Requires-Dist: envdot; extra == "all"
Dynamic: author
Dynamic: author-email
Dynamic: classifier
Dynamic: description
Dynamic: description-content-type
Dynamic: home-page
Dynamic: keywords
Dynamic: license
Dynamic: license-file
Dynamic: maintainer
Dynamic: maintainer-email
Dynamic: platform
Dynamic: provides-extra
Dynamic: requires-dist
Dynamic: summary
